mohsinlib/__init__.py
mohsinlib/math.py
mohsinlib-0.0.2.dist-info/METADATA
mohsinlib-0.0.2.dist-info/WHEEL
mohsinlib-0.0.2.dist-info/top_level.txt
mohsinlib-0.0.2.dist-info/RECORD
