Metadata-Version: 2.1
Name: mohsinlib
Version: 0.0.2
Requires-Dist: importlib-metadata ; python_version < "3.10"
